rship_sdk/__init__.py
rship_sdk/client.py
rship_sdk/models.py
rship_sdk/utils.py
rship_sdk/proxies/action.py
rship_sdk/proxies/emitter.py
rship_sdk/proxies/event_track.py
rship_sdk/proxies/instance.py
rship_sdk/proxies/target.py
rship_sdk-0.1.43.dist-info/METADATA
rship_sdk-0.1.43.dist-info/WHEEL
rship_sdk-0.1.43.dist-info/licenses/LICENSE
rship_sdk-0.1.43.dist-info/RECORD
