Metadata-Version: 2.4
Name: rship-sdk
Version: 0.1.43
Summary: Add your description here
License-File: LICENSE
Requires-Python: >=3.11
Requires-Dist: myko
